{
    "repositories": [
      {
        "id": 1,
        "name": "design-system",
        "full_name": "johnDoe/React-Project",
        "description": "A simple React app project",
        "html_url": "https://github.com/johnDoe/React-Project",
        "language": "JavaScript",
        "storage": "7230kb",
        "update": "2",
        "visibility":"private",
        "stargazers_count": 120,
        "forks_count": 15,
        "created_at": "2023-01-01T00:00:00Z",
        "updated_at": "2023-12-01T00:00:00Z",
        "owner": {
          "login": "johnDoe",
          "avatar_url": "https://avatars.githubusercontent.com/u/12345678?v=4"
        }
      },
      {
        "id": 2,
        "name": "codent-ci-pp",
        "full_name": "janeDoe/Node.js-API",
        "description": "A REST API built with Node.js and Express",
        "html_url": "https://github.com/janeDoe/Node.js-API",
        "language": "JavaScript",
        "storage": "3430kb",
        "update": "5",
        "visibility":"public",
        "stargazers_count": 85,
        "forks_count": 22,
        "created_at": "2022-06-15T00:00:00Z",
        "updated_at": "2023-11-25T00:00:00Z",
        "owner": {
          "login": "janeDoe",
          "avatar_url": "https://avatars.githubusercontent.com/u/87654321?v=4"
        }
      },
      {
        "id": 3,
        "name": "analytics-dashboard",
        "full_name": "alexSmith/AI-Image-Generator",
        "description": "An AI-based image generator app",
        "html_url": "https://github.com/alexSmith/AI-Image-Generator",
        "language": "Python",
        "storage": "8230kb",
        "update": "5",
        "visibility":"public",
        "stargazers_count": 200,
        "forks_count": 30,
        "created_at": "2023-03-25T00:00:00Z",
        "updated_at": "2023-12-10T00:00:00Z",
        "owner": {
          "login": "alexSmith",
          "avatar_url": "https://avatars.githubusercontent.com/u/56789101?v=4"
        }
      },
      {
        "id": 4,
        "name": "mobile-app",
        "full_name": "alexSmith/AI-Image-Generator",
        "description": "An AI-based image generator app",
        "html_url": "https://github.com/alexSmith/AI-Image-Generator",
        "language": "Python",
        "storage": "8230kb",
        "update": "6",
        "visibility":"public",
        "stargazers_count": 200,
        "forks_count": 30,
        "created_at": "2023-03-25T00:00:00Z",
        "updated_at": "2023-12-10T00:00:00Z",
        "owner": {
          "login": "alexSmith",
          "avatar_url": "https://avatars.githubusercontent.com/u/56789101?v=4"
        }
      },
      {
        "id": 5,
        "name": "e-commerce-platform",
        "full_name": "alexSmith/AI-Image-Generator",
        "description": "An AI-based image generator app",
        "html_url": "https://github.com/alexSmith/AI-Image-Generator",
        "language": "Python",
        "storage": "8230kb",
        "update": "7",
        "visibility":"public",
        "stargazers_count": 200,
        "forks_count": 30,
        "created_at": "2023-03-25T00:00:00Z",
        "updated_at": "2023-12-10T00:00:00Z",
        "owner": {
          "login": "alexSmith",
          "avatar_url": "https://avatars.githubusercontent.com/u/56789101?v=4"
        }
      },
      {
        "id": 6,
        "name": "blog-website",
        "full_name": "alexSmith/AI-Image-Generator",
        "description": "An AI-based image generator app",
        "html_url": "https://github.com/alexSmith/AI-Image-Generator",
        "language": "javascript",
        "storage": "6030kb",
        "update": "9",
        "visibility":"private",
        "stargazers_count": 200,
        "forks_count": 30,
        "created_at": "2023-03-25T00:00:00Z",
        "updated_at": "2023-12-10T00:00:00Z",
        "owner": {
          "login": "alexSmith",
          "avatar_url": "https://avatars.githubusercontent.com/u/56789101?v=4"
        }
      },
      {
        "id": 7,
        "name": "cms-dashboard",
        "full_name": "alexSmith/AI-Image-Generator",
        "description": "An AI-based image generator app",
        "html_url": "https://github.com/alexSmith/AI-Image-Generator",
        "language": "PHP",
        "storage": "8230kb",
        "update": "10",
        "visibility":"private",
        "stargazers_count": 200,
        "forks_count": 30,
        "created_at": "2023-03-25T00:00:00Z",
        "updated_at": "2023-12-10T00:00:00Z",
        "owner": {
          "login": "alexSmith",
          "avatar_url": "https://avatars.githubusercontent.com/u/56789101?v=4"
        }
      },
      {
        "id": 8,
        "name": "analytics-form",
        "full_name": "alexSmith/AI-Image-Generator",
        "description": "An AI-based image generator app",
        "html_url": "https://github.com/alexSmith/AI-Image-Generator",
        "language": "HTML",
        "storage": "6030kb",
        "update": "9",
        "visibility":"public",
        "stargazers_count": 200,
        "forks_count": 30,
        "created_at": "2023-03-25T00:00:00Z",
        "updated_at": "2023-12-10T00:00:00Z",
        "owner": {
          "login": "alexSmith",
          "avatar_url": "https://avatars.githubusercontent.com/u/56789101?v=4"
        }
      },
      {
        "id": 9,
        "name": "brand-site",
        "full_name": "alexSmith/AI-Image-Generator",
        "description": "An AI-based image generator app",
        "html_url": "https://github.com/alexSmith/AI-Image-Generator",
        "language": "javascript",
        "storage": "6030kb",
        "update": "9",
        "visibility":"public",
        "stargazers_count": 200,
        "forks_count": 30,
        "created_at": "2023-03-25T00:00:00Z",
        "updated_at": "2023-12-10T00:00:00Z",
        "owner": {
          "login": "alexSmith",
          "avatar_url": "https://avatars.githubusercontent.com/u/56789101?v=4"
        }
      },
      {
        "id": 10,
        "name": "mood-tracker",
        "full_name": "alexSmith/AI-Image-Generator",
        "description": "An AI-based image generator app",
        "html_url": "https://github.com/alexSmith/AI-Image-Generator",
        "language": "javascript",
        "storage": "6030kb",
        "update": "9",
        "visibility":"public",
        "stargazers_count": 200,
        "forks_count": 30,
        "created_at": "2023-03-25T00:00:00Z",
        "updated_at": "2023-12-10T00:00:00Z",
        "owner": {
          "login": "alexSmith",
          "avatar_url": "https://avatars.githubusercontent.com/u/56789101?v=4"
        }
      },
      {
        "id": 11,
        "name": "product-review",
        "full_name": "alexSmith/AI-Image-Generator",
        "description": "An AI-based image generator app",
        "html_url": "https://github.com/alexSmith/AI-Image-Generator",
        "language": "React",
        "storage": "6030kb",
        "update": "9",
        "visibility":"public",
        "stargazers_count": 200,
        "forks_count": 30,
        "created_at": "2023-03-25T00:00:00Z",
        "updated_at": "2023-12-10T00:00:00Z",
        "owner": {
          "login": "alexSmith",
          "avatar_url": "https://avatars.githubusercontent.com/u/56789101?v=4"
        }
      },
      {
        "id": 12,
        "name": "analytics-dashboard",
        "full_name": "alexSmith/AI-Image-Generator",
        "description": "An AI-based image generator app",
        "html_url": "https://github.com/alexSmith/AI-Image-Generator",
        "language": "javascript",
        "storage": "6030kb",
        "update": "9",
        "visibility":"public",
        "stargazers_count": 200,
        "forks_count": 30,
        "created_at": "2023-03-25T00:00:00Z",
        "updated_at": "2023-12-10T00:00:00Z",
        "owner": {
          "login": "alexSmith",
          "avatar_url": "https://avatars.githubusercontent.com/u/56789101?v=4"
        }
      },
      {
        "id": 13,
        "name": "analytics-tracker",
        "full_name": "alexSmith/AI-Image-Generator",
        "description": "An AI-based image generator app",
        "html_url": "https://github.com/alexSmith/AI-Image-Generator",
        "language": "PHP",
        "storage": "6030kb",
        "update": "9",
        "visibility":"public",
        "stargazers_count": 200,
        "forks_count": 30,
        "created_at": "2023-03-25T00:00:00Z",
        "updated_at": "2023-12-10T00:00:00Z",
        "owner": {
          "login": "alexSmith",
          "avatar_url": "https://avatars.githubusercontent.com/u/56789101?v=4"
        }
      },
      {
        "id": 14,
        "name": "analytics-dashboard",
        "full_name": "alexSmith/AI-Image-Generator",
        "description": "An AI-based image generator app",
        "html_url": "https://github.com/alexSmith/AI-Image-Generator",
        "language": "Java",
        "storage": "6030kb",
        "update": "9",
        "visibility":"public",
        "stargazers_count": 200,
        "forks_count": 30,
        "created_at": "2023-03-25T00:00:00Z",
        "updated_at": "2023-12-10T00:00:00Z",
        "owner": {
          "login": "alexSmith",
          "avatar_url": "https://avatars.githubusercontent.com/u/56789101?v=4"
        }
      },
      {
        "id": 15,
        "name": "analytics-dashboard",
        "full_name": "alexSmith/AI-Image-Generator",
        "description": "An AI-based image generator app",
        "html_url": "https://github.com/alexSmith/AI-Image-Generator",
        "language": "Swift",
        "storage": "6030kb",
        "update": "9",
        "visibility":"public",
        "stargazers_count": 200,
        "forks_count": 30,
        "created_at": "2023-03-25T00:00:00Z",
        "updated_at": "2023-12-10T00:00:00Z",
        "owner": {
          "login": "alexSmith",
          "avatar_url": "https://avatars.githubusercontent.com/u/56789101?v=4"
        }
      },
      {
        "id": 16,
        "name": "analytics-dashboard",
        "full_name": "alexSmith/AI-Image-Generator",
        "description": "An AI-based image generator app",
        "html_url": "https://github.com/alexSmith/AI-Image-Generator",
        "language": "Python",
        "storage": "6030kb",
        "update": "9",
        "visibility":"public",
        "stargazers_count": 200,
        "forks_count": 30,
        "created_at": "2023-03-25T00:00:00Z",
        "updated_at": "2023-12-10T00:00:00Z",
        "owner": {
          "login": "alexSmith",
          "avatar_url": "https://avatars.githubusercontent.com/u/56789101?v=4"
        }
      },
      {
        "id": 17,
        "name": "analytics-dashboard",
        "full_name": "alexSmith/AI-Image-Generator",
        "description": "An AI-based image generator app",
        "html_url": "https://github.com/alexSmith/AI-Image-Generator",
        "language": "javascript",
        "storage": "6030kb",
        "update": "9",
        "visibility":"public",
        "stargazers_count": 200,
        "forks_count": 30,
        "created_at": "2023-03-25T00:00:00Z",
        "updated_at": "2023-12-10T00:00:00Z",
        "owner": {
          "login": "alexSmith",
          "avatar_url": "https://avatars.githubusercontent.com/u/56789101?v=4"
        }
      },
      {
        "id": 18,
        "name": "analytics-dashboard",
        "full_name": "alexSmith/AI-Image-Generator",
        "description": "An AI-based image generator app",
        "html_url": "https://github.com/alexSmith/AI-Image-Generator",
        "language": "Java",
        "storage": "6030kb",
        "update": "9",
        "visibility":"public",
        "stargazers_count": 200,
        "forks_count": 30,
        "created_at": "2023-03-25T00:00:00Z",
        "updated_at": "2023-12-10T00:00:00Z",
        "owner": {
          "login": "alexSmith",
          "avatar_url": "https://avatars.githubusercontent.com/u/56789101?v=4"
        }
      },
      {
        "id": 19,
        "name": "analytics-dashboard",
        "full_name": "alexSmith/AI-Image-Generator",
        "description": "An AI-based image generator app",
        "html_url": "https://github.com/alexSmith/AI-Image-Generator",
        "language": "javascript",
        "storage": "6030kb",
        "update": "9",
        "visibility":"public",
        "stargazers_count": 200,
        "forks_count": 30,
        "created_at": "2023-03-25T00:00:00Z",
        "updated_at": "2023-12-10T00:00:00Z",
        "owner": {
          "login": "alexSmith",
          "avatar_url": "https://avatars.githubusercontent.com/u/56789101?v=4"
        }
      },
      {
        "id": 20,
        "name": "analytics-dashboard",
        "full_name": "alexSmith/AI-Image-Generator",
        "description": "An AI-based image generator app",
        "html_url": "https://github.com/alexSmith/AI-Image-Generator",
        "language": "javascript",
        "storage": "6030kb",
        "update": "9",
        "visibility":"public",
        "stargazers_count": 200,
        "forks_count": 30,
        "created_at": "2023-03-25T00:00:00Z",
        "updated_at": "2023-12-10T00:00:00Z",
        "owner": {
          "login": "alexSmith",
          "avatar_url": "https://avatars.githubusercontent.com/u/56789101?v=4"
        }
      },
      {
        "id": 21,
        "name": "analytics-dashboard",
        "full_name": "alexSmith/AI-Image-Generator",
        "description": "An AI-based image generator app",
        "html_url": "https://github.com/alexSmith/AI-Image-Generator",
        "language": "javascript",
        "storage": "6030kb",
        "update": "9",
        "visibility":"public",
        "stargazers_count": 200,
        "forks_count": 30,
        "created_at": "2023-03-25T00:00:00Z",
        "updated_at": "2023-12-10T00:00:00Z",
        "owner": {
          "login": "alexSmith",
          "avatar_url": "https://avatars.githubusercontent.com/u/56789101?v=4"
        }
      },
      {
        "id": 22,
        "name": "analytics-dashboard",
        "full_name": "alexSmith/AI-Image-Generator",
        "description": "An AI-based image generator app",
        "html_url": "https://github.com/alexSmith/AI-Image-Generator",
        "language": "javascript",
        "storage": "6030kb",
        "update": "9",
        "visibility":"public",
        "stargazers_count": 200,
        "forks_count": 30,
        "created_at": "2023-03-25T00:00:00Z",
        "updated_at": "2023-12-10T00:00:00Z",
        "owner": {
          "login": "alexSmith",
          "avatar_url": "https://avatars.githubusercontent.com/u/56789101?v=4"
        }
      },
      {
        "id": 23,
        "name": "analytics-dashboard",
        "full_name": "alexSmith/AI-Image-Generator",
        "description": "An AI-based image generator app",
        "html_url": "https://github.com/alexSmith/AI-Image-Generator",
        "language": "javascript",
        "storage": "6030kb",
        "update": "9",
        "visibility":"public",
        "stargazers_count": 200,
        "forks_count": 30,
        "created_at": "2023-03-25T00:00:00Z",
        "updated_at": "2023-12-10T00:00:00Z",
        "owner": {
          "login": "alexSmith",
          "avatar_url": "https://avatars.githubusercontent.com/u/56789101?v=4"
        }
      },
      {
        "id": 24,
        "name": "analytics-dashboard",
        "full_name": "alexSmith/AI-Image-Generator",
        "description": "An AI-based image generator app",
        "html_url": "https://github.com/alexSmith/AI-Image-Generator",
        "language": "javascript",
        "storage": "6030kb",
        "update": "9",
        "visibility":"public",
        "stargazers_count": 200,
        "forks_count": 30,
        "created_at": "2023-03-25T00:00:00Z",
        "updated_at": "2023-12-10T00:00:00Z",
        "owner": {
          "login": "alexSmith",
          "avatar_url": "https://avatars.githubusercontent.com/u/56789101?v=4"
        }
      },
      {
        "id": 25,
        "name": "analytics-dashboard",
        "full_name": "alexSmith/AI-Image-Generator",
        "description": "An AI-based image generator app",
        "html_url": "https://github.com/alexSmith/AI-Image-Generator",
        "language": "javascript",
        "storage": "6030kb",
        "update": "9",
        "visibility":"public",
        "stargazers_count": 200,
        "forks_count": 30,
        "created_at": "2023-03-25T00:00:00Z",
        "updated_at": "2023-12-10T00:00:00Z",
        "owner": {
          "login": "alexSmith",
          "avatar_url": "https://avatars.githubusercontent.com/u/56789101?v=4"
        }
      },
      {
        "id": 26,
        "name": "analytics-dashboard",
        "full_name": "alexSmith/AI-Image-Generator",
        "description": "An AI-based image generator app",
        "html_url": "https://github.com/alexSmith/AI-Image-Generator",
        "language": "javascript",
        "storage": "6030kb",
        "update": "9",
        "visibility":"public",
        "stargazers_count": 200,
        "forks_count": 30,
        "created_at": "2023-03-25T00:00:00Z",
        "updated_at": "2023-12-10T00:00:00Z",
        "owner": {
          "login": "alexSmith",
          "avatar_url": "https://avatars.githubusercontent.com/u/56789101?v=4"
        }
      },
      {
        "id": 27,
        "name": "analytics-dashboard",
        "full_name": "alexSmith/AI-Image-Generator",
        "description": "An AI-based image generator app",
        "html_url": "https://github.com/alexSmith/AI-Image-Generator",
        "language": "javascript",
        "storage": "6030kb",
        "update": "9",
        "visibility":"public",
        "stargazers_count": 200,
        "forks_count": 30,
        "created_at": "2023-03-25T00:00:00Z",
        "updated_at": "2023-12-10T00:00:00Z",
        "owner": {
          "login": "alexSmith",
          "avatar_url": "https://avatars.githubusercontent.com/u/56789101?v=4"
        }
      },
      {
        "id": 28,
        "name": "analytics-dashboard",
        "full_name": "alexSmith/AI-Image-Generator",
        "description": "An AI-based image generator app",
        "html_url": "https://github.com/alexSmith/AI-Image-Generator",
        "language": "javascript",
        "storage": "6030kb",
        "update": "9",
        "visibility":"public",
        "stargazers_count": 200,
        "forks_count": 30,
        "created_at": "2023-03-25T00:00:00Z",
        "updated_at": "2023-12-10T00:00:00Z",
        "owner": {
          "login": "alexSmith",
          "avatar_url": "https://avatars.githubusercontent.com/u/56789101?v=4"
        }
      },
      {
        "id": 29,
        "name": "analytics-dashboard",
        "full_name": "alexSmith/AI-Image-Generator",
        "description": "An AI-based image generator app",
        "html_url": "https://github.com/alexSmith/AI-Image-Generator",
        "language": "javascript",
        "storage": "6030kb",
        "update": "9",
        "visibility":"public",
        "stargazers_count": 200,
        "forks_count": 30,
        "created_at": "2023-03-25T00:00:00Z",
        "updated_at": "2023-12-10T00:00:00Z",
        "owner": {
          "login": "alexSmith",
          "avatar_url": "https://avatars.githubusercontent.com/u/56789101?v=4"
        }
      },
      {
        "id": 30,
        "name": "analytics-dashboard",
        "full_name": "alexSmith/AI-Image-Generator",
        "description": "An AI-based image generator app",
        "html_url": "https://github.com/alexSmith/AI-Image-Generator",
        "language": "javascript",
        "storage": "6030kb",
        "update": "9",
        "visibility":"public",
        "stargazers_count": 200,
        "forks_count": 30,
        "created_at": "2023-03-25T00:00:00Z",
        "updated_at": "2023-12-10T00:00:00Z",
        "owner": {
          "login": "alexSmith",
          "avatar_url": "https://avatars.githubusercontent.com/u/56789101?v=4"
        }
      },
      {
        "id": 31,
        "name": "analytics-dashboard",
        "full_name": "alexSmith/AI-Image-Generator",
        "description": "An AI-based image generator app",
        "html_url": "https://github.com/alexSmith/AI-Image-Generator",
        "language": "javascript",
        "storage": "6030kb",
        "update": "9",
        "visibility":"public",
        "stargazers_count": 200,
        "forks_count": 30,
        "created_at": "2023-03-25T00:00:00Z",
        "updated_at": "2023-12-10T00:00:00Z",
        "owner": {
          "login": "alexSmith",
          "avatar_url": "https://avatars.githubusercontent.com/u/56789101?v=4"
        }
      },
      {
        "id": 32,
        "name": "analytics-dashboard",
        "full_name": "alexSmith/AI-Image-Generator",
        "description": "An AI-based image generator app",
        "html_url": "https://github.com/alexSmith/AI-Image-Generator",
        "language": "javascript",
        "storage": "6030kb",
        "update": "9",
        "visibility":"public",
        "stargazers_count": 200,
        "forks_count": 30,
        "created_at": "2023-03-25T00:00:00Z",
        "updated_at": "2023-12-10T00:00:00Z",
        "owner": {
          "login": "alexSmith",
          "avatar_url": "https://avatars.githubusercontent.com/u/56789101?v=4"
        }
      },
      {
        "id": 33,
        "name": "analytics-dashboard",
        "full_name": "alexSmith/AI-Image-Generator",
        "description": "An AI-based image generator app",
        "html_url": "https://github.com/alexSmith/AI-Image-Generator",
        "language": "javascript",
        "storage": "6030kb",
        "update": "9",
        "visibility":"public",
        "stargazers_count": 200,
        "forks_count": 30,
        "created_at": "2023-03-25T00:00:00Z",
        "updated_at": "2023-12-10T00:00:00Z",
        "owner": {
          "login": "alexSmith",
          "avatar_url": "https://avatars.githubusercontent.com/u/56789101?v=4"
        }
      }

    ]
  }
  